[{"constructorId":"mclaren","constructorName":"McLaren","position":1,"points":713.0,"drivers":["Lando Norris","Oscar Piastri"],"driverPoints":[357.0,356.0],"teamColor":"#ff8000"},{"constructorId":"ferrari","constructorName":"Ferrari","position":2,"points":356.0,"drivers":["Charles Leclerc","Lewis Hamilton"],"driverPoints":[210.0,146.0],"teamColor":"#e80020"},{"constructorId":"mercedes","constructorName":"Mercedes","position":3,"points":355.0,"drivers":["George Russell","Andrea Kimi Antonelli"],"driverPoints":[258.0,97.0],"teamColor":"#27f4d2"},{"constructorId":"red_bull","constructorName":"Red Bull","position":4,"points":346.0,"drivers":["Max Verstappen","Yuki Tsunoda"],"driverPoints":[321.0,28.0],"teamColor":"#0600ef"},{"constructorId":"williams","constructorName":"Williams","position":5,"points":111.0,"drivers":["Alexander Albon","Carlos Sainz"],"driverPoints":[73.0,38.0],"teamColor":"#00a0dd"},{"constructorId":"rb","constructorName":"Racing Bulls","position":6,"points":72.0,"drivers":["Isack Hadjar","Liam Lawson","Yuki Tsunoda"],"driverPoints":[39.0,30.0,28.0],"teamColor":"#fcd700"},{"constructorId":"aston_martin","constructorName":"Aston Martin","position":7,"points":69.0,"drivers":["Fernando Alonso","Lance Stroll"],"driverPoints":[37.0,32.0],"teamColor":"#00665f"},{"constructorId":"haas","constructorName":"Haas","position":8,"points":62.0,"drivers":["Oliver Bearman","Esteban Ocon"],"driverPoints":[32.0,30.0],"teamColor":"#b6babd"},{"constructorId":"sauber","constructorName":"Kick Sauber","position":9,"points":60.0,"drivers":["Nico H\u00fclkenberg","Gabriel Bortoleto"],"driverPoints":[41.0,19.0],"teamColor":"#00e700"},{"constructorId":"alpine","constructorName":"Alpine","position":10,"points":20.0,"drivers":["Pierre Gasly","Franco Colapinto","Jack Doohan"],"driverPoints":[20.0,0.0,0.0],"teamColor":"#ff87bc"}]